mediarepo/__main__.py
mediarepo-0.6.3.dist-info/METADATA
mediarepo-0.6.3.dist-info/WHEEL
mediarepo-0.6.3.dist-info/entry_points.txt
mediarepo-0.6.3.dist-info/RECORD
